[
    {
        "id": "Koryx Darnell_0",
        "conversation": [
            {
                "speaker": "interviewer",
                "content": "Thank you for agreeing to meet with me today, Koryx. To kick things off, can you tell me a little about your background and how you got started in your work as an inventor and street vendor?"
            },
            {
                "speaker": "interviewee",
                "content": "Of course! I grew up here in Zaun, and seeing the pollution firsthand really impacted me. I lost a close friend to respiratory issues a few years ago, and that ignited my passion for creating solutions. I started making small filtration devices to sell at my stand. It felt like I could make a difference, even if it was on a small scale."
            }
        ],
        "raw_keywords": [
            "Zaun",
            "pollution",
            "respiratory issues",
            "close friend",
            "passion",
            "creating solutions",
            "filtration devices",
            "stand",
            "make a difference",
            "small scale"
        ],
        "title": "\"Passion for Change: Koryx's Journey as an Inventor\""
    },
    {
        "id": "Koryx Darnell_1",
        "conversation": [
            {
                "speaker": "interviewer",
                "content": "That’s really inspiring. I can imagine how personal experiences like that can drive someone to take action. What specific challenges did you face when you first started making these devices?"
            },
            {
                "speaker": "interviewee",
                "content": "Well, initially, I struggled with sourcing materials. Many components are hard to come by due to their cost or scarcity, especially in a city like Zaun that’s so industrialized. It’s like a constant battle just to find affordable resources to create my products."
            },
            {
                "speaker": "interviewer",
                "content": "I can understand how that would be difficult. And these barriers, do they affect your ability to reach more people with your devices?"
            },
            {
                "speaker": "interviewee",
                "content": "Absolutely. I can only make a limited number of devices, and it takes time to handcraft each one. I’d love to scale up and help more people, but without support or funding, I can’t make that leap."
            }
        ],
        "raw_keywords": [
            "sourcing materials",
            "components",
            "cost",
            "scarcity",
            "Zaun",
            "industrialized",
            "battle",
            "affordable resources",
            "create",
            "devices",
            "time",
            "handcraft",
            "scale up",
            "help",
            "support",
            "funding",
            "leap"
        ],
        "title": "\"Challenges of Innovation in Resource-Limited Environments\""
    },
    {
        "id": "Koryx Darnell_2",
        "conversation": [
            {
                "speaker": "interviewer",
                "content": "Have you explored any partnerships with local organizations or businesses to address these challenges?"
            },
            {
                "speaker": "interviewee",
                "content": "I’ve tried, but most organizations are focused on broader initiatives. They’re often disconnected from the grassroots level where the real community needs are. I believe support should come from the community first, not just top-down solutions that don’t address our specific issues here."
            }
        ],
        "raw_keywords": [
            "organizations",
            "broader initiatives",
            "disconnected",
            "grassroots level",
            "community needs",
            "support",
            "top-down solutions",
            "specific issues"
        ],
        "title": "Community-Centric Solutions vs. Broader Initiatives"
    },
    {
        "id": "Koryx Darnell_3",
        "conversation": [
            {
                "speaker": "interviewer",
                "content": "That makes sense. Local knowledge can be invaluable. Can you tell me how residents respond to your filtration devices?"
            },
            {
                "speaker": "interviewee",
                "content": "The response has been great! People appreciate that I’m understanding their struggles and creating affordable options. I often hear stories about how it’s helping families cope with the air pollution, which fuels my motivation. But there’s still a lot of skepticism about whether basic devices can make enough of a difference."
            },
            {
                "speaker": "interviewer",
                "content": "What kind of feedback do you get from those who use your devices?"
            },
            {
                "speaker": "interviewee",
                "content": "Users often talk about feeling a sense of relief when they breathe cleaner air. Some even mention that they sleep better at night. But others are always asking for something stronger or more effective, which is a challenge I’m constantly thinking about."
            }
        ],
        "raw_keywords": [
            "response",
            "great",
            "understanding",
            "struggles",
            "affordable options",
            "stories",
            "families",
            "cope",
            "air pollution",
            "motivation",
            "skepticism",
            "basic devices",
            "difference",
            "sense of relief",
            "breathe",
            "cleaner air",
            "sleep better",
            "stronger",
            "effective",
            "challenge"
        ],
        "title": "Community Feedback on Air Filtration Devices Effectiveness"
    },
    {
        "id": "Koryx Darnell_4",
        "conversation": [
            {
                "speaker": "interviewer",
                "content": "That’s really compelling. Have you thought about how you could improve or innovate your devices to address those requests?"
            },
            {
                "speaker": "interviewee",
                "content": "Definitely! I’ve been experimenting with different filtration methods, but again, I run into material access issues. I want to create a three-stage device that’s more efficient, but it’ll take investment and resources I currently don’t have."
            }
        ],
        "raw_keywords": [
            "experimenting",
            "filtration methods",
            "material access issues",
            "three-stage device",
            "efficient",
            "investment",
            "resources"
        ],
        "title": "Innovating Filtration Devices: Challenges and Solutions"
    },
    {
        "id": "Koryx Darnell_5",
        "conversation": [
            {
                "speaker": "interviewer",
                "content": "If you could get some support— funding or materials—what’s your vision for the next steps?"
            },
            {
                "speaker": "interviewee",
                "content": "I’d love to create a workshop for others in the community to learn about building devices and understanding pollution. More minds working together could drive innovation, and I believe education is key. Empowering local residents would help us tackle the pollution problem more effectively."
            }
        ],
        "raw_keywords": [
            "workshop",
            "community",
            "building devices",
            "understanding pollution",
            "innovation",
            "education",
            "empowering local residents",
            "tackle",
            "pollution problem"
        ],
        "title": "Empowering Community Through Workshops on Pollution Solutions"
    },
    {
        "id": "Koryx Darnell_6",
        "conversation": [
            {
                "speaker": "interviewer",
                "content": "That sounds like a fantastic initiative! Have you considered reaching out to schools or community centers for collaboration?"
            },
            {
                "speaker": "interviewee",
                "content": "I have, but there seems to be a lack of engagement on that front. I often feel like my voice gets lost in the larger conversations about Zaun’s issues. It’s frustrating because we all need to come together."
            }
        ],
        "raw_keywords": [
            "lack of engagement",
            "voice",
            "larger conversations",
            "Zaun’s issues",
            "frustrating",
            "come together"
        ],
        "title": "Collaboration Challenges in Community Engagement Initiatives"
    },
    {
        "id": "Koryx Darnell_7",
        "conversation": [
            {
                "speaker": "interviewer",
                "content": "I can’t imagine how discouraging that must feel. How do you keep your motivation up despite these obstacles?"
            },
            {
                "speaker": "interviewee",
                "content": "Honestly, it’s the people. Every time someone tells me that my device made a difference in their lives, it reinvigorates me. I also believe that change takes time; you just have to be persistent."
            }
        ],
        "raw_keywords": [
            "people",
            "device",
            "difference",
            "lives",
            "reinvigorates",
            "change",
            "time",
            "persistent"
        ],
        "title": "Staying Motivated Through Challenges and Impactful Feedback"
    },
    {
        "id": "Koryx Darnell_8",
        "conversation": [
            {
                "speaker": "interviewer",
                "content": "That’s such an admirable mindset, Koryx. Have you thought about documenting your work or experiences in a more visible way, perhaps through social media or a blog?"
            },
            {
                "speaker": "interviewee",
                "content": "I’ve toyed with the idea! I think social media could reach a wider audience, especially to showcase the real-life impacts of pollution and the solutions we’re developing here. But I worry about having enough time to maintain it."
            },
            {
                "speaker": "interviewer",
                "content": "That’s a valid concern. Perhaps even teaming up with someone who could help run it might ease that burden for you?"
            },
            {
                "speaker": "interviewee",
                "content": "That’s a great idea! I haven’t thought about collaborating in that way. It might also connect me with people who have resources I need."
            }
        ],
        "raw_keywords": [
            "social media",
            "wider audience",
            "real-life impacts",
            "pollution",
            "solutions",
            "collaborating",
            "connect",
            "resources"
        ],
        "title": "Exploring Social Media for Environmental Advocacy"
    },
    {
        "id": "Koryx Darnell_9",
        "conversation": [
            {
                "speaker": "interviewer",
                "content": "Definitely! Networking can be so powerful, especially in an industrial city like Zaun. Are there any particular groups or networks you think would be beneficial to explore?"
            },
            {
                "speaker": "interviewee",
                "content": "I've heard about some activist groups forming, focusing on environmental justice. Linking up with them could amplify our voices and push for tougher regulations on pollution. That might also attract attention to grassroots innovations like mine."
            }
        ],
        "raw_keywords": [
            "activist groups",
            "environmental justice",
            "amplify",
            "voices",
            "tougher regulations",
            "pollution",
            "grassroots innovations"
        ],
        "title": "Exploring Networking for Environmental Activism in Zaun"
    },
    {
        "id": "Koryx Darnell_10",
        "conversation": [
            {
                "speaker": "interviewer",
                "content": "That sounds promising! It seems like there’s a hunger for change in Zaun, and initiatives led by the community could really lead to impactful legislation. Have you thought about any particular regulations that you would advocate for?"
            },
            {
                "speaker": "interviewee",
                "content": "I think stricter emissions standards for industries are crucial. There's also a need for more transparency about what's being dumped into our water systems. The community deserves to be informed about what's affecting our health."
            },
            {
                "speaker": "interviewer",
                "content": "Absolutely, transparency is key. Do you find that the residents feel empowered to hold industries accountable?"
            },
            {
                "speaker": "interviewee",
                "content": "Not really. Many feel powerless against larger corporations. A lot of people I talk to just want to get by—they don't have the energy or resources to push back."
            }
        ],
        "raw_keywords": [
            "stricter emissions standards",
            "industries",
            "transparency",
            "water systems",
            "community",
            "health",
            "powerless",
            "corporations",
            "get by",
            "energy",
            "resources",
            "push back"
        ],
        "title": "Empowering Community Accountability in Zaun's Environmental Issues"
    },
    {
        "id": "Koryx Darnell_11",
        "conversation": [
            {
                "speaker": "interviewer",
                "content": "That’s really disheartening. Helping to foster a sense of community involvement could be crucial in that regard. What community initiatives do you think would encourage more involvement?"
            },
            {
                "speaker": "interviewee",
                "content": "I think organizing clean-up events or informational workshops in neighborhoods would help. It’s a way to unite people while educating them about pollution. If they feel a sense of ownership in their environment, they might be compelled to take action."
            },
            {
                "speaker": "interviewer",
                "content": "I love that idea! Mobilizing the community can create a powerful change. Have you had any interest from local businesses to support such initiatives?"
            },
            {
                "speaker": "interviewee",
                "content": "Some have shown limited interest, but I think many are afraid of rocking the boat. They don’t want to draw attention to their practices, fearing backlash."
            },
            {
                "speaker": "interviewer",
                "content": "I can see how that could be a barrier. Building trust and showing the potential benefits of collaboration might help change that mindset."
            },
            {
                "speaker": "interviewee",
                "content": "Yes, any partnerships that show it’s a win-win could change the narrative. If businesses see they can improve their public image while genuinely helping the community, that could make a difference."
            }
        ],
        "raw_keywords": [
            "organizing",
            "clean-up events",
            "informational workshops",
            "neighborhoods",
            "unite",
            "educating",
            "pollution",
            "sense of ownership",
            "environment",
            "take action",
            "limited interest",
            "afraid",
            "rocking the boat",
            "backlash",
            "partnerships",
            "win-win",
            "change the narrative",
            "businesses",
            "public image",
            "helping the community",
            "make a difference"
        ],
        "title": "Fostering Community Involvement through Local Initiatives"
    },
    {
        "id": "Koryx Darnell_12",
        "conversation": [
            {
                "speaker": "interviewer",
                "content": "Exactly. A collaborative effort could lead to innovative solutions, both environmentally and economically. Before we wrap up, is there anything you’d like to add regarding the future of Zaun?"
            },
            {
                "speaker": "interviewee",
                "content": "Just that we need to rethink how we approach these problems. Zaun has the creativity and potential to thrive while being environmentally responsible. But it takes collective effort to make that a reality."
            },
            {
                "speaker": "interviewer",
                "content": "Thank you so much for sharing your insights and experiences today, Koryx. It's clear that your work is impactful, and I hope this conversation helps highlight the importance of community-driven solutions in Zaun."
            },
            {
                "speaker": "interviewee",
                "content": "Thank you for listening! I hope it raises awareness and inspires action in improving our beloved Zaun."
            }
        ],
        "raw_keywords": [
            "rethink",
            "approach",
            "problems",
            "Zaun",
            "creativity",
            "potential",
            "thrive",
            "environmentally responsible",
            "collective effort",
            "reality",
            "awareness",
            "inspires",
            "action",
            "improving",
            "beloved"
        ],
        "title": "\"Collaborative Solutions for a Sustainable Future in Zaun\""
    }
]